tests/__init__.py
tests/test_forms.py
tests/test_models.py
tests/testapp/__init__.py
tests/testapp/manage.py
tests/testapp/home/__init__.py
tests/testapp/home/forms.py
tests/testapp/home/models.py
tests/testapp/home/migrations/0001_initial.py
tests/testapp/home/migrations/0002_custom_form_builder_pages.py
tests/testapp/home/migrations/__init__.py
tests/testapp/testapp/__init__.py
tests/testapp/testapp/settings.py
tests/testapp/testapp/urls.py
tests/testapp/testapp/wsgi.py
wagtailcaptcha/__init__.py
wagtailcaptcha/forms.py
wagtailcaptcha/models.py
wagtail_django_simple_captcha-1.0.dist-info/LICENSE
wagtail_django_simple_captcha-1.0.dist-info/METADATA
wagtail_django_simple_captcha-1.0.dist-info/WHEEL
wagtail_django_simple_captcha-1.0.dist-info/top_level.txt
wagtail_django_simple_captcha-1.0.dist-info/RECORD
