Metadata-Version: 2.1
Name: wagtail-django-simple-captcha
Version: 1.0
Summary: A simple Captcha field for Wagtail form pages.
Home-page: http://github.com/acarasimon96/wagtail-django-simple-captcha
Author: Timothy Bautista (acarasimon96)
Author-email: acarasimon96@pm.me
License: MIT
Platform: UNKNOWN
Classifier: Environment :: Web Environment
Classifier: Framework :: Django
Classifier: Framework :: Wagtail
Classifier: Framework :: Wagtail :: 1
Classifier: Framework :: Wagtail :: 2
Classifier: Intended Audience :: Developers
Classifier: License :: OSI Approved :: MIT License
Classifier: Operating System :: OS Independent
Classifier: Programming Language :: Python
Classifier: Programming Language :: Python :: 2
Classifier: Programming Language :: Python :: 2.7
Classifier: Programming Language :: Python :: 3
Classifier: Programming Language :: Python :: 3.4
Classifier: Programming Language :: Python :: 3.5
Classifier: Programming Language :: Python :: 3.6
Classifier: Programming Language :: Python :: 3.7
Classifier: Programming Language :: Python :: 3.8
Classifier: Topic :: Internet :: WWW/HTTP
Classifier: Topic :: Internet :: WWW/HTTP :: Dynamic Content
Requires-Dist: django-simple-captcha
Provides-Extra: docs
Provides-Extra: testing
Requires-Dist: tox (<2.4,>=2.3.1) ; extra == 'testing'
Requires-Dist: coverage (<4.2,>=4.1.0) ; extra == 'testing'
Requires-Dist: flake8 (<3.3,>=3.2.0) ; extra == 'testing'
Requires-Dist: isort (==4.2.5) ; extra == 'testing'
Requires-Dist: wagtail (>=2.0) ; extra == 'testing'
